LingerGRN/Benchmk.py
LingerGRN/Compare.py
LingerGRN/LINGER_tr.py
LingerGRN/LL_net.py
LingerGRN/LingerGRN.py
LingerGRN/TF_activity.py
LingerGRN/perturb.py
LingerGRN/preprocess.py
LingerGRN/pseudo_bulk.py
LingerGRN-1.105.dist-info/LICENSE
LingerGRN-1.105.dist-info/METADATA
LingerGRN-1.105.dist-info/WHEEL
LingerGRN-1.105.dist-info/top_level.txt
LingerGRN-1.105.dist-info/RECORD
