Metadata-Version: 2.1
Name: LingerGRN
Version: 1.105
Summary: Gene regulatory network inference
Home-page: https://github.com/Durenlab/LINGER
Author: Kaya Yuan
Author-email: qyyuan33@gmail.com
License: MIT
License-File: LICENSE
Requires-Dist: torch
Requires-Dist: scipy ==1.11.3
Requires-Dist: numpy ==1.24.3
Requires-Dist: pandas ==2.0.3
Requires-Dist: shap ==0.42.0
Requires-Dist: scikit-learn ==1.3.0
Requires-Dist: joblib ==1.3.2
Requires-Dist: matplotlib ==3.8.0
Requires-Dist: seaborn ==0.13.0
Requires-Dist: statsmodels ==0.14.1
Requires-Dist: umap-learn
Requires-Dist: scanpy ==1.9.5
Requires-Dist: anndata ==0.9.2
Requires-Dist: pybedtools ==0.10.0
Requires-Dist: rpy2 ==3.5.16
